sygn/__init__.py
sygn/__main__.py
sygn/api.py
sygn/core/__init__.py
sygn/core/entities/__init__.py
sygn/core/entities/base_component.py
sygn/core/entities/observation.py
sygn/core/entities/observatory/__init__.py
sygn/core/entities/observatory/array_configuration.py
sygn/core/entities/observatory/beam_combination_scheme.py
sygn/core/entities/observatory/observatory.py
sygn/core/entities/photon_sources/__init__.py
sygn/core/entities/photon_sources/base_photon_source.py
sygn/core/entities/photon_sources/exozodi.py
sygn/core/entities/photon_sources/local_zodi.py
sygn/core/entities/photon_sources/planet.py
sygn/core/entities/photon_sources/star.py
sygn/core/entities/scene.py
sygn/core/entities/settings.py
sygn/core/processing/__init__.py
sygn/core/processing/data_generator.py
sygn/io/__init__.py
sygn/io/fits_writer.py
sygn/io/txt_reader.py
sygn/io/validators.py
sygn/io/yaml_handler.py
sygn/py.typed
sygn/util/__init__.py
sygn/util/blackbody.py
sygn/util/grid.py
sygn/util/helpers.py
sygn/util/matrix.py
sygn/util/noise_generator.py
sygn-0.0.5.dist-info/entry_points.txt
sygn-0.0.5.dist-info/LICENSE
sygn-0.0.5.dist-info/METADATA
sygn-0.0.5.dist-info/WHEEL
sygn-0.0.5.dist-info/RECORD
