Metadata-Version: 2.1
Name: sygn
Version: 0.0.5
Summary: SYGN
Home-page: https://github.com/pahuber/sygn
License: MIT
Author: Philipp A. Huber
Author-email: huberph@phys.ethz.ch
Requires-Python: >=3.9,<3.11
Classifier: Development Status :: 4 - Beta
Classifier: License :: OSI Approved :: MIT License
Classifier: Programming Language :: Python :: 3
Classifier: Programming Language :: Python :: 3.9
Classifier: Programming Language :: Python :: 3.10
Requires-Dist: astropy (>=5.3,<6)
Requires-Dist: click (>=8.0.1)
Requires-Dist: numba (>=0.59.0,<0.60.0)
Requires-Dist: numpy (>=1.26.3,<2.0.0)
Requires-Dist: poliastro (>=0.17.0,<0.18.0)
Requires-Dist: pydantic (>=2.6.1,<3.0.0)
Requires-Dist: spectres (>=2.2.0,<3.0.0)
Requires-Dist: tqdm (>=4.66.1,<5.0.0)
Project-URL: Changelog, https://github.com/pahuber/sygn/releases
Project-URL: Documentation, https://sygn.readthedocs.io
Project-URL: Repository, https://github.com/pahuber/sygn
